[{"name":"Arken","url":"https://www.karkafeerna.fi/fi/lounas","openHours":"MA-PE 8.00-14.30 \n(LOUNAS 11 - 14)\nSuljettu 19.6 - 14.8","menu":[{"name":"Makkarastroganoffia ","price":"2,95€","type":"Lounas"},{"name":"Porkkanakroketteja ja pinaattimuhennosta ","price":"2,95€","type":"Vegaaninen"}]},{"name":"Aurum","url":"https://www.karkafeerna.fi/fi/lounas","openHours":"MA-TO 7.30-14.3\n(LOUNAS 10.30-14)","menu":[{"name":"Jauhelihapihvi, viherpippuri kastiketta ja perunat ","price":"2,95€","type":"Lounas"},{"name":"Vegaaninen biryani \"makkaralla\" ja kikherneillä, aioli ","price":"2,95€","type":"Vegaaninen"}]},{"name":"Aurum Bistro","url":"https://www.karkafeerna.fi/fi/lounas","openHours":"Ei lounasta tänään","menu":[]},{"name":"Kåren","url":"https://www.karkafeerna.fi/fi/lounas","openHours":"Ei lounasta tänään","menu":[]},{"name":"ASA","url":"https://www.karkafeerna.fi/fi/lounas","openHours":"Ei lounasta tänään","menu":[]},{"name":"Macciavelli","url":"https://www.unica.fi/ravintolat/Yliopisto/Macciavelli/","openHours":"10.30-15.00","menu":[{"name":"Kasvispihvit (*, G, Veg) ()","price":"2,95 / 6,50 / 7,70 / 9,20","type":"KASVISLOUNAS"},{"name":"Broileri-nauta-bolognesekastiketta (*, G, L, M) ()","price":"2,95 / 6,50 / 7,70 / 9,20","type":"LOUNAS"},{"name":"Broileriwokkia (G, L, M) ()","price":"2,95 / 6,50 / 7,70 / 9,20","type":"LOUNAS"},{"name":"Valkosipulimajoneesia (G, Veg) ()","price":"Hintaa ei annettu","type":"KYLMÄT KASTIKKEET - valintasi mukaan"},{"name":"Luomutäysjyväpennepastaa (L, M, Veg) ()\nPaahdettua perunaa (G, Veg) ()","price":"Hintaa ei annettu","type":"ENERGIALISÄKKEET - valintasi mukaan"},{"name":"Kaksi jäätelöä yhden hinnalla :-) ()","price":"Hintaa ei annettu","type":"JÄLKIRUOKA"}]},{"name":"Deli Pharma","url":"https://www.unica.fi/ravintolat/Kupittaa/deli-pharma/","openHours":"10:30-14:00","menu":[{"name":"Aurajuusto-kasvispizzaa (A, L)","price":"5,60 / 10,70","type":"KASVISBISTRO"},{"name":"Kylmäsavukirjolohi-juustokastiketta (*, A, ILM, L)\nRigatonipastaa (A, L, M, Veg)\nPastajuustoraastetta (A, G, L)","price":"5,60 / 10,70","type":"BISTRO1"},{"name":"Rosmariinilla maustettua broilerinfilettä (*, G, L, M)\nTomaattimajoneesia (A, G, ILM, L, M)\nHöyrytettyä riisiä (G, L, M, Veg)","price":"5,60 / 10,70","type":"BISTRO"},{"name":"Paahdettuja porkkanoita (G, L, M)","price":"Hintaa ei annettu","type":"LÄMMIN KASVISLISUKE"},{"name":"Valkosuklaamoussea (VL,G) ()","price":"1,80","type":"JÄLKIRUOKA"}]},{"name":"Sigyn","url":"https://www.unica.fi/ravintolat/taidekampus/Sigyn/","openHours":"11.00-14.00","menu":[{"name":"Juustopastavuokaa (A, L, VS)","price":"2,95 / 10,10","type":"KASVIS LOUNAS"},{"name":"Sveitsinleike (A, L)\nPaahdetulla sipulilla maustettua perunasosetta (A, L)","price":"5,60 / 13,50","type":"DELI LOUNAS"}]},{"name":"Flavoria","url":"https://www.sodexo.fi/ravintolat/flavoria-medisiina-d","openHours":"Lounas MA-PE 10:30-13:30\nKahvila MA-TO 07:30-15:30\nKahvila PE 07:30-14:30","menu":[{"name":"Pähkinäistä pestopastaa","price":"2,95 € / 9,35 €","type":"FROM THE FIELD-VEGAN"},{"name":"Jauhelihakastiketta ja perunamuusia","price":"2,95 € / 9,35 €","type":"From our favorites 1"},{"name":"Broiler caesarsalaatti","price":"2,95 € / 8,30 €","type":"FROM THE GARDEN (kahvilasta)"}]}]