[{"name":"Arken","url":"https://www.karkafeerna.fi/fi/lounas","openHours":"MA-PE 8-14.30\n(LOUNAS 11-14)","menu":[{"name":"Lohipihvejä ja kermaviilikastiketta ","price":"2,95€","type":"Lounas"},{"name":"Kanabiryania ja tomaatti-currykastiketta ","price":"2,95€","type":"Lounas"},{"name":"Vindaloo currya soijapyöryköillä ja basmatiriisillä ","price":"2,95€","type":"Vegaaninen"},{"name":"KAHVIPUOLELTA: ","price":"Hintaa ei annettu","type":"Lounas"},{"name":"Arken patonki (Klo. 10 alkaen) ","price":"2,95€","type":"Lounas"}]},{"name":"Aurum","url":"https://www.karkafeerna.fi/fi/lounas","openHours":"MA-PE 7.30-14.30\n(LOUNAS 10.30-14)","menu":[{"name":"Punainen kanacurry, riisi ","price":"2,95€","type":"Lounas"},{"name":"Tacoliha-perunalaatikko ","price":"2,95€","type":"Lounas"},{"name":"Hernepihvit ja majssi-valkosipulikastiketta, perunat ","price":"2,95€","type":"Vegaaninen"},{"name":"Bataattikeitto chilillä ja kookosmaidolla, krutongit ","price":"2,65€","type":"Vegaaninen"}]},{"name":"Aurum Bistro","url":"https://www.karkafeerna.fi/fi/lounas","openHours":"MA-PE 11-14","menu":[{"name":"Paholaisen burgeri ","price":"4,25 - 15,00€","type":"Kasvis"},{"name":"Bulgogi burgeri ","price":"4,25 - 15,00€","type":"Lounas"},{"name":"Grillattu lohi ja tilli-voikastike ","price":"4,25 - 15,00€","type":"Lounas"},{"name":"Caesarsalaatti ","price":"4,25 - 15,00€","type":"Lounas"},{"name":"Grillattu kana ja Maltankastike ","price":"4,25 - 15,00€","type":"Lounas"}]},{"name":"Kåren","url":"https://www.karkafeerna.fi/fi/lounas","openHours":"MA-PE 11-14","menu":[{"name":"Lihapullia tomaattikastikkeessa,pastaa ","price":"2,95€","type":"Lounas"},{"name":"Feta-kasvispihvit, riisiä ja tsatsikia ","price":"2,95€","type":"Kasvis"},{"name":"Bataatti-inkiväärisosekeitto, krutongit/ raejuustoa ","price":"2,95€","type":"Vegaaninen"}]},{"name":"ASA","url":"https://www.karkafeerna.fi/fi/lounas","openHours":"Ei lounasta tänään","menu":[]},{"name":"Assarin Ullakko","url":"https://www.unica.fi/ravintolat/Yliopisto/assarin-ullakko/","openHours":"10.30-17.45","menu":[{"name":"Tomaattista soija-paprikapataa (*, A, G, ILM, L, M, Veg, VS)","price":"2,95 / 7,50 / 9,00","type":"BRYGGE VEGAANINEN LOUNAS"},{"name":"Feta-pinaatti-cashewpähkinäpizzaa (A, VL)","price":"2,95  / 7,50 / 9,00","type":"ASEMA 1-2  10.30-18"},{"name":"Broileria Kung Po (*, A, G, L, M, VS)","price":"2,95 / 7,50 / 9,00","type":"ASEMA 1-2  10.30-20"}]},{"name":"Macciavelli","url":"https://www.unica.fi/ravintolat/Yliopisto/Macciavelli/","openHours":"Ei lounasta tänään","menu":[]},{"name":"Galilei","url":"https://www.unica.fi/ravintolat/Yliopisto/galilei/","openHours":"Ei lounasta tänään","menu":[]},{"name":"Monttu ja Mercatori","url":"https://www.unica.fi/ravintolat/Yliopisto/monttu-ja-mercatori/","openHours":"Ei lounasta tänään","menu":[]},{"name":"Deli Pharma","url":"https://www.unica.fi/ravintolat/Kupittaa/deli-pharma/","openHours":"Ei lounasta tänään","menu":[]},{"name":"Delica","url":"https://www.unica.fi/ravintolat/Kupittaa/delica/","openHours":"11.00-15.00","menu":[{"name":"Bataatti-kookoskermacurrya (A, ILM, L, M, Veg, VS)\nBasmatiriisiä (G, L, M, Veg)","price":"2,95/ 7,50 / 9,00","type":"Vegaaninen kasvislounas"},{"name":"Riisipuuroa (A, G, L)\nMansikkakiisseliä (G, L, M, Veg)","price":"2,25  / 6,00","type":"PUUROLOUNAS"},{"name":"Lohikeittoa A, G, L & saaristolaisleipää A, L ()","price":"2,95 / 7,50  / 9,00","type":"LOUNAS 2"},{"name":"Broileria ja kasviksia teriyakikastikkeessa (A, L, M, VS)\nBasmatiriisiä (G, L, M, Veg)","price":"2,95 / 7,50 / 9,00","type":"LOUNAS 1"}]},{"name":"Linus","url":"https://www.unica.fi/ravintolat/Kupittaa/linus/","openHours":"Ei lounasta tänään","menu":[]},{"name":"Kisälli","url":"https://www.unica.fi/ravintolat/Kupittaa/kisalli/","openHours":"Ei lounasta tänään","menu":[]},{"name":"Sigyn","url":"https://www.unica.fi/ravintolat/taidekampus/Sigyn/","openHours":"Ei lounasta tänään","menu":[]},{"name":"Unican Kulma","url":"https://www.unica.fi/ravintolat/Muut/unican-kulma/","openHours":"11:00-16:00","menu":[{"name":"Bataattisosekeittoa (*, A, G, ILM, L, M, Veg)","price":"2,95 / 8,50","type":"Kulman vegaaninen keittolounas"},{"name":"Savupalvipatonki (A, L)","price":"2,95 / 8,50","type":"Kulman patonkilounas"}]},{"name":"Flavoria","url":"https://www.sodexo.fi/ravintolat/flavoria-medisiina-d","openHours":"Ei lounasta tänään","menu":[]}]