[{"name":"Arken","url":"https://www.karkafeerna.fi/fi/lounas","openHours":"MA-TO 8-15\n/>(LOUNAS 11-14.30)\n/>PE 8-14.30\n/>(LOUNAS 11-14)","menu":[{"name":"Lihapullia kermakastikkeessa  ","price":"2,70€","type":"Lounas"},{"name":"Kasvisbiryania ja curry-tomaattikastiketta ","price":"2,70€","type":"Vegaaninen"},{"name":"Arken patonki (Klo. 10 alkaen) ","price":"2,70","type":"Lounas"}]},{"name":"Aurum","url":"https://www.karkafeerna.fi/fi/lounas","openHours":"MA-TO 7.30-14.30\n/>LOUNAS 10.30-14.00","menu":[{"name":"Aurum salad Bowl buffet ","price":"2,70€","type":"Lounas"},{"name":"Kana-pastagratiini ja parmesaani ","price":"2,70€","type":"Lounas"},{"name":"Jauhelihakeittoa ","price":"2,70€","type":"Lounas"},{"name":"Intialainen Kashmir Rogan Josh sojapalapataa ","price":"2,70€","type":"Vegaaninen"},{"name":"Kikherne-porkkanapihvit, tomaatti-pestokastiketta ","price":"2,70€","type":"Vegaaninen"}]},{"name":"Aurum Bistro","url":"https://www.karkafeerna.fi/fi/lounas","openHours":"Bistro Meny 11-14","menu":[{"name":"Caesarsalaatti ","price":"4,00 - 5,35€","type":"Lounas"},{"name":"Grillattu kana ","price":"4,00 - 5,35€","type":"Lounas"},{"name":"Grillattu lohi ","price":"4,00 - 5,35€","type":"Lounas"}]},{"name":"Kåren","url":"https://www.karkafeerna.fi/fi/lounas","openHours":"MA-PE 11-14","menu":[{"name":"Paneroitu broilerin leike, currykastiketta ja riisiä ","price":"2,70€","type":"Lounas"},{"name":"Vegaaninen Kaalipata, puolukkaa ","price":"2,70€","type":"Vegaaninen"},{"name":"Katkarapu-kananmuna salaatti ","price":"2,70","type":"Lounas"}]},{"name":"ASA","url":"https://www.karkafeerna.fi/fi/lounas","openHours":"Ei lounasta tänään","menu":[]},{"name":"Assarin Ullakko","url":"https://www.unica.fi/ravintolat/Yliopisto/assarin-ullakko/","openHours":"10.30-19.45","menu":[{"name":"Porkkana-kaalipihvejä (* ,A ,G ,L ,M)\nKermaviilikastiketta tuoreista yrteistä (A ,G ,ILM ,L)","price":"2,70 / 7,50 / 9,00","type":"ASEMA 1-2 Klo 10.30-16.00"},{"name":"Kikherne-kasviskeittoa (A ,G ,ILM ,L ,M ,Veg ,VS)","price":"2,70 / 7,50 / 9,00","type":"ASEMA 3 KEITTO Klo 10.30-16.00"},{"name":"Vöner- täytettä (* ,ILM ,L ,M ,Veg ,VS)\nTäysjyvävehnätortilla (A ,L ,M ,Veg)","price":"2,70 / 7,50 / 9,00","type":"VEGAANINEN LOUNAS"},{"name":"Lindströminpihvejä (A ,L ,M)\nMeiramikastiketta (A ,ILM ,L)\nKeitettyjä perunoita (* ,A ,G ,ILM ,L ,M ,Veg)","price":"2,70 / 7,50 / 9,00","type":"ASEMA 1-2 Klo 10.30-20"},{"name":"Hapanimelää broileria thaimaalaisittain (* ,A ,G ,ILM ,L ,M ,VS)\nHöyrytettyä tummaa riisiä (* ,G ,L ,M ,Veg)","price":"2,70 / 7,50 / 9,00","type":"ASEMA 1-2 Klo 10.30-16"},{"name":"Rapeita kalapaloja (* ,A ,L ,M)\nChili-jugurttikastiketta (A ,G ,ILM ,L)\nPaahdettuja lohkoperunoita (G ,ILM ,L ,M ,Veg)","price":"2,70 / 7,50 / 9,00","type":"ASEMA 1-2 Klo 16-20.00"},{"name":"Raparperi-kaurapaistosta ja kermavaahtoa L, A 1,50 € ()","price":"Hintaa ei annettu","type":"PÄIVÄN JÄLKIRUOKA"}]},{"name":"Macciavelli","url":"https://www.unica.fi/ravintolat/Yliopisto/Macciavelli/","openHours":"10.30-17.00","menu":[{"name":"Härkis-lasagne (L) ()","price":"2,70 / 6,00 / 7,50 / 9,00","type":"KASVISLOUNAS"},{"name":"Maissi-kvinoapihvejä (* ,A ,L ,M ,VS)\nTzatsikia (A ,G ,ILM ,L ,VS)","price":"2,70 / 6,00 / 7,50 / 9,00","type":"KASVISLOUNAS"},{"name":"Luomutofua ja kasviksia soijakastikkeessa (* ,A ,G ,ILM ,L ,M ,Veg)\nHöyrytettyä tummaa riisiä (* ,G ,L ,M ,Veg)","price":"2,70 / 6,00 / 7,50 / 9,00","type":"KASVISLOUNAS"},{"name":"Janssoninkiusausta (A ,G ,ILM ,L)","price":"2,70 / 6,00 / 7,50 / 9,00","type":"LOUNAS"},{"name":"Broileri-nuudelikeittoa (* ,A ,ILM ,L ,M)","price":"2,70 / 6,00 / 7,50 / 9,00","type":"KEITTOLOUNAS"},{"name":"Hedelmämousse (L, G) ()","price":"1,50","type":"JÄLKKÄRI"}]},{"name":"Galilei","url":"https://www.unica.fi/ravintolat/Yliopisto/galilei/","openHours":"10.30 - 14.30","menu":[{"name":"Talon kasvispihvit / pyörykät ()\nBasilikamajoneesi (A ,G ,L ,M ,Veg)\nPaahdettuja uuniperunoita (* ,G ,ILM ,L ,M ,Veg)","price":"2,70 /7,50 / 9,00","type":"KASVISLOUNAS"},{"name":"Pyttipannua ja paistettu kananmuna (A ,G ,L ,M)","price":"2,70 /7,50 / 9,00","type":"LOUNAS"},{"name":"Nizzan salaattia (A ,G ,ILM ,L ,M ,VS)","price":"5,35 /7,50 / 9,00","type":"KAHVION SALAATTIBUFFA"},{"name":"Linssi-kasviskeittoa (* ,A ,G ,ILM ,L ,M ,Veg ,VS)","price":"2,70 /7,50 / 9,00","type":"KAHVION VEGAANINEN KASVISKEITTO"},{"name":"Suklaakiisseliä (A ,G)","price":"1,80","type":"PÄIVÄN JÄLKIRUOKA"}]},{"name":"Monttu ja Mercatori","url":"https://www.unica.fi/ravintolat/Yliopisto/monttu-ja-mercatori/","openHours":"11:00-14:00","menu":[{"name":"Raastepihvejä (* ,A ,L ,M)\nRuohosipulikermaviilikastiketta (A ,G ,ILM ,L)\nRyppyperunoita (* ,G ,ILM ,L ,M ,Veg)","price":"2,70/7,50/9,00","type":"Kasvislounas"},{"name":"Kebab-pastavuokaa (A ,L ,VS)","price":"2,70/7,50/9,00","type":"Lounas"},{"name":"Butter Chicken (A ,G ,L ,VS)\nKauden kasviksia (G ,L ,M ,Veg)\nJasminriisiä (G ,L ,M ,Veg)","price":"5,35/9,90/10,50","type":"Deli lounas tarjolla klo 11.00 - 13.30"}]},{"name":"Dental","url":"https://www.unica.fi/ravintolat/Kupittaa/dental/","openHours":"10.45-13.30","menu":[{"name":"Kasvisbolognese-pennevuokaa (* ,A ,ILM ,L ,M ,Veg)","price":"2,70/7,50/9,00","type":"KASVISLOUNAS"},{"name":"Kalapuikkoja (* ,A ,L ,M)\nTillikermaviilikastiketta (A ,G ,ILM ,L)\nPerunasosetta (* ,A ,G ,ILM ,L)","price":"2,70/7,50/9,00","type":"KOTILOUNAS"},{"name":"Paahdettua broileria ja ratatouillea (A ,G ,L ,M ,VS)\nPapas arrugadas -perunoita (* ,G ,ILM ,L ,M ,Veg)","price":"5,35/10,50","type":"DELILOUNAS"}]},{"name":"Deli Pharma","url":"https://www.unica.fi/ravintolat/Kupittaa/deli-pharma/","openHours":null,"menu":[{"name":"Porkkana-pestolasagnea (* ,A ,L ,VS)","price":"5,30 / 10,20","type":"BISTRO"},{"name":"Paistettuja muikkuja (A ,ILM ,L)\nTilli-voisulaa (A ,L)\nPaahdetulla sipulilla maustettua perunasosetta (A ,L)","price":"5,30 / 10,20","type":"BISTRO"},{"name":"Paahdettua broileria ja sitruunapolentaa (A ,G ,L)","price":"5,30 / 10,20","type":"BISTRO"},{"name":"Vadelma-mansikkavispipuuroa (A ,L ,M ,Veg)\nVaniljakermavaahtoa (A ,G ,L)","price":"1,50","type":"JÄLKIRUOKA"}]},{"name":"Delica","url":"https://www.unica.fi/ravintolat/Kupittaa/delica/","openHours":"10:30-16:00","menu":[{"name":"Raastepihvejä (* ,A ,L ,M)\nRuohosipulikermaviilikastiketta (A ,G ,ILM ,L)\nPapas arrugadas -perunoita (* ,G ,ILM ,L ,M ,Veg)","price":"2,70 / 7,00 / 8,10","type":"KASVISLOUNAS"},{"name":"Pyttipannua ja paistettu kananmuna (A ,G ,L ,M)\nPaistettu kananmuna (A ,G ,L ,M)","price":"2,70 / 7,00/ 8,10","type":"LOUNAS"},{"name":"Kirjolohta ja kasviksia inkiväärikastikkeessa (* ,A ,G ,ILM ,L ,M)\nHöyrytettyä tummaa riisiä (* ,G ,L ,M ,Veg)","price":"2,70 / 7,00 / 8,10","type":"LOUNAS"}]},{"name":"Linus","url":"https://www.unica.fi/ravintolat/Kupittaa/linus/","openHours":"10.30-13.30","menu":[{"name":"Kasvisbolognese-pennevuokaa (* ,A ,ILM ,L ,M ,Veg)","price":"2,70/7,50/9,00 €","type":"VEGAANINEN KASVISLOUNAS"},{"name":"Kalapuikkoja (* ,A ,L ,M)\nTillikermaviilikastiketta (A ,G ,ILM ,L)\nPerunasosetta (* ,A ,G ,ILM ,L)","price":"2,70/7,50/9,00 €","type":"KOTIRUOKALOUNAS"},{"name":"Broilerin paistia (G ,L ,M)","price":"2,70/7,50/9,00 €","type":"SALAATTILOUNAS"},{"name":"Paahdettua broileria ja ratatouillea (A ,G ,L ,M ,VS)\nPapas arrugadas -perunoita (* ,G ,ILM ,L ,M ,Veg)","price":"5,35/10,50 €","type":"DELILOUNAS"},{"name":"Valkosuklaamoussea (A ,G)","price":"1,50 €","type":"JÄLKIRUOKA"}]},{"name":"Kisälli","url":"https://www.unica.fi/ravintolat/Kupittaa/kisalli/","openHours":"10.30-14.30 (bistro 10.30-13.30)","menu":[{"name":"Kasvispataa (* ,A ,G ,ILM ,L ,M ,Veg)\nHöyrytettyä tummaa riisiä (* ,G ,L ,M ,Veg)","price":"2,70 / 6,00 / 7,50 / 9,00","type":"ASEMA 1 / KASVISRUOKA"},{"name":"Chilimajoneesia (A ,G ,L)\nPapas arrugadas -perunoita (* ,G ,ILM ,L ,M ,Veg)\nJauhelihapihvi (A,L,M) ()","price":"2,70 / 6,00 / 7,50 / 9,00","type":"ASEMA 1 / KOTIRUOKA"},{"name":"Ranskalaisia perunoita (G ,ILM ,L ,M ,Veg)\nTulinen nyhtöpossu briossihampurilainen (A ,L ,M)\nBBQ -majoneesia (A ,G ,L ,M ,Veg ,VS)","price":"5,35 / 10,50","type":"BISTRO"},{"name":"Salaattiasemalla tarjolla runsas kattaus tuoreita kasviksia ja vihanneksia, sekä paljon erilaisia herkullisia lisukkeita. ()","price":"salaattiannokset alkaen 3,60€","type":"SALAATTIASEMA"},{"name":"Mariannerahkaa (A ,L)","price":"1,50 / 1,80","type":"JÄLKIRUOKA"},{"name":"Kauden kasviksia (G ,L ,M ,Veg)\nMetsästäjänleike (A ,L)\nPaahdettuja yrttiperunoita (G ,ILM ,L ,M ,Veg)","price":"12,00","type":"KAIVOMESTARIN LOUNAS"}]},{"name":"Sigyn","url":"https://www.unica.fi/ravintolat/taidekampus/Sigyn/","openHours":"11.00-14.00","menu":[{"name":"Pinaattikeittoa ()\nKeitetty kananmuna (A ,G ,L ,M)","price":"2,70 / 6,30 / 8,20","type":"KAHVILA & KELLARI"},{"name":"Kirjolohta tandoori-smetanakastikkeessa (A ,G ,L)\nPerunasosetta (A ,G ,L)","price":"5,35 / 7,00 / 9,90","type":"KAHVILA klo 11-14"},{"name":"Broilerikiusausta (* ,A ,G ,L)","price":"2,70 / 7,00 / 9,90","type":"KELLARI"},{"name":"Päivän jälkiruoka ()","price":"1,50- 3,00","type":"PÄIVÄN JÄLKIRUOKA"}]},{"name":"Unican Kulma","url":"https://www.unica.fi/ravintolat/Muut/unican-kulma/","openHours":"11:00-14:30","menu":[{"name":"Kasvisbolognese-pennevuokaa (* ,A ,ILM ,L ,M ,Veg)","price":"2,70/8,90","type":"Kulman vegaaninen kasvislounas"},{"name":"Kalapuikkoja (* ,A ,L ,M)\nTillikermaviilikastiketta (A ,G ,ILM ,L)\nPerunasosetta (* ,A ,G ,ILM ,L)","price":"2,70/8,90","type":"Kulman lounas"},{"name":"Paahdettua broileria ja ratatouillea (A ,G ,L ,M ,VS)\nPapas arrugadas -perunoita (* ,G ,ILM ,L ,M ,Veg)","price":"5,35/9,50","type":"KULMAN  DELI LOUNAS"}]},{"name":"Kasvisravintola Piccu Maccia","url":"https://www.unica.fi/ravintolat/Muut/piccu-maccia/","openHours":"11.00-14.30","menu":[{"name":"Kauden salaattisekoitusta (G ,L ,M ,Veg)\nYrttimaustettua bataattia (G ,L ,M ,Veg)\nKeitetty kananmuna (A ,G ,L ,M)\nHovimestarin jättipapuja (A ,G ,L ,M ,Veg)\nOliivivihanneksia (G ,L ,M ,Veg ,VS)\nAvokadohummusta (A ,G ,L ,M ,Veg ,VS)\nKetjap manis -marinoitua perunaa (A ,G ,ILM ,L ,M ,Veg)\nLinssi-hernesalaattia (A ,L ,M ,Veg)\nChilipaahdettua ananasta (G, Veg) ()\nShotit: Mustaherukka-rosmariinishotti (G, Veg) ja Porkkana-inkiväärishotti (G, Veg) ()\nProtskut: Halloumia (G) ja kukkakaaliwingsit (Veg) ()","price":"5,35 / 9,40 / 9,40 / 10,50","type":"GREEN BUFFET - sis. lämpimän kasvislisäkkeen ja keiton"},{"name":"Kauden kasviksia (G ,L ,M ,Veg)","price":"Hintaa ei annettu","type":"LÄMMIN KASVISLISÄKE (Green Buffet)"},{"name":"Täyteläistä mustajuurisosekeittoa (A ,G ,ILM ,L ,VS)\nPaahdettuja siemeniä (G ,L ,M ,Veg)","price":"2,70 / 6,00 / 7,50 / 9,00","type":"KASVISKEITTO (sisältyy Green buffettiin)"},{"name":"Nyhtökauratäytettä (* ,A ,ILM ,L ,M ,Veg)\nTacoja (G ,L ,M ,Veg)\nLime-chilikauragurttikastiketta (A ,ILM ,L ,M ,Veg)","price":"5,35 / 9,40 / 9,40 / 10,50","type":"G R E E N  D E L I #1 sis. side salaatin"},{"name":"Paahdettua kirjolohta (* ,A ,G ,ILM ,L ,M)\nCurry-valkosipulikastiketta (A ,G ,ILM ,L ,VS)\nPaahdettuja perunoita (* ,G ,ILM ,L ,M ,Veg)\nKauden kasviksia (G ,L ,M ,Veg)","price":"5,35 / 9,40 / 9,40 / 10,50","type":"D E L I #2 sis. side salaatin"}]},{"name":"Flavoria","url":"https://www.sodexo.fi/ravintolat/flavoria-medisiina-d","openHours":"Lounas MA-PE 10:30-13:30\nKahvila MA-TO 07:30-15:30\nKahvila PE 07:30-14:30","menu":[{"name":"Herkkusieni-härkäpapupastaa","price":"2,70 € / 8,35 €","type":"FROM THE FIELD-VEGAN"},{"name":"Nakkistroganoff ja perunaa","price":"2,70 € / 8,35 €","type":"FROM OUR FAVORITES 2"},{"name":"Pestokuorrutettua seitä ja lämmintä jyväpastasalaattia","price":"2,70 € / 8,35 €","type":"FROM OUR FAVORITES 1"},{"name":"Halloumi burger ja bataattiranskalaiset","price":"5,35 € / 9,80 €","type":"FROM THE KITCHEN (grillistä)"},{"name":"Vuohenjuusto-punajuurisalaatti","price":"2,70 € / 7,30 €","type":"FROM THE GARDEN (kahvilasta)"},{"name":"Lounaspatonki kreikkalaisella juusto-kasvistäytteellä","price":"2,70 € / 7,30 €","type":"FROM OUR BAKERY (kahvilasta)"},{"name":"Brownie","price":"1,80 €","type":"FROM THE SWEET"}]}]