[{"name":"Arken","url":"https://www.karkafeerna.fi/fi/lounas","openHours":"MA-TO 8-15\n/>(LOUNAS 11-14.30)\n/>PE 8-14.30\n/>(LOUNAS 11-14)","menu":[{"name":"Gulassipataa naudanlihalla ja kermaviilillä  ","price":"2,70€","type":"Lounas"},{"name":"Lounas tänään kl.11-13 ","price":"Hintaa ei annettu","type":"Lounas"},{"name":"Pestopastaa grillatuilla vihanneksilla, paahdetuilla siemenillä ja Quornilla ","price":"2,70€","type":"Vegaaninen"},{"name":"Vegaanimakkarastroganoff ","price":"2,70€","type":"Vegaaninen"},{"name":"Arken patonki (Klo. 10 alkaen) ","price":"2,70","type":"Lounas"}]},{"name":"Aurum","url":"https://www.karkafeerna.fi/fi/lounas","openHours":"MA-TO 7.30-18.00, PE 7.30-14.30, LA 12.00-15.00 \n/>LOUNAS MA-TO 10.30-18.00, PE 10.30-14.30","menu":[{"name":"Aurum Bowl buffet ","price":"4,00 - 5,35€","type":"Lounas"},{"name":"Kanan koipireisi ja punaviinikastiketta, riisi ","price":"2,70€","type":"Lounas"},{"name":"Bouillabaisse (kalakeitto) aiolilla ","price":"2,70€","type":"Lounas"},{"name":"Chili con carne, riisi ","price":"2,70€","type":"Lounas"},{"name":"Härkis-nuudeliwokki vihanneksilla, chilikastiketta ","price":"2,70€","type":"Vegaaninen"},{"name":"Kidneypapu-ratatouille ja perunat ","price":"2,70€","type":"Vegaaninen"},{"name":"Hernekeitto savustetulla kinkulla ","price":"2,70€","type":"Lounas"},{"name":"Vegaani hernekeitto  ","price":"2,40€","type":"Vegaaninen"},{"name":"Aurumin oma pannukakku hillolla ja vispikermalla ","price":"1,50 - 3,00€","type":"Lounas"},{"name":"Aurumin oma vegaani ja gluteeniton pannukakku hillolla ja vispikermalla ","price":"1,50 - 3,00€","type":"Vegaaninen"}]},{"name":"Aurum Bistro","url":"https://www.karkafeerna.fi/fi/lounas","openHours":"Bistro Meny 11-14","menu":[{"name":"Caesarsalaatti ","price":"4,00 - 5,35€","type":"Lounas"},{"name":"Grillattu kana ","price":"4,00 - 5,35€","type":"Lounas"},{"name":"Grillattu lohi ","price":"4,00 - 5,35€","type":"Lounas"}]},{"name":"Kåren","url":"https://www.karkafeerna.fi/fi/lounas","openHours":"MA-PE 11-14","menu":[{"name":"Limellä ja korianterilla paneerattu kalapala, yrttijogurttikastiketta ja perunat ","price":"2,70€","type":"Lounas"},{"name":"Broilersalaatti ","price":"2,70","type":"Lounas"},{"name":"Asiakkaiden toivomuksesta: Hernekeittoa savukinkulla ","price":"2,70€","type":"Lounas"},{"name":"Kasvishernekeittoa soijarouheella ","price":"2,70€","type":"Vegaaninen"},{"name":"Pannukakkua kermavaahdolla ja hillolla ","price":"1,50 - 3,00€","type":"Kasvis"}]},{"name":"ASA","url":"https://www.karkafeerna.fi/fi/lounas","openHours":"Ei lounasta tänään","menu":[]},{"name":"Assarin Ullakko","url":"https://www.unica.fi/ravintolat/Yliopisto/assarin-ullakko/","openHours":"10.30-19:45","menu":[{"name":"Falafel-pyöryköitä (A ,L ,M ,Veg ,VS)\nTzatsikia (A ,G ,ILM ,L ,VS)","price":"2,70 / 7,50 / 9,00","type":"ASEMA 1-2 Klo 10.30-16.00"},{"name":"Raejuustoa (A ,G ,L)\nTomaattikeittoa (* ,A ,ILM ,L)","price":"2,70 / 7,50 / 9,00","type":"ASEMA 3 KEITTO Klo 10.30-16.00"},{"name":"Kreikkalaista kasvispataa *, VEG, G, A ()","price":"2,70 / 7,50 / 9,00","type":"VEGAANINEN LOUNAS"},{"name":"Harissalla maustettua kalkkunapataa (* ,A ,G ,L ,VS)\nHöyrytettyä tummaa riisiä (* ,G ,L ,M ,Veg)","price":"2,70 / 7,50 / 9,00","type":"ASEMA 1-2 Klo 10.30-20"},{"name":"Välimerellistä seitiä (* ,A ,G ,L ,VS)\nKeitettyjä perunoita (* ,A ,G ,ILM ,L ,M ,Veg)","price":"2,70 / 7,50 / 9,00","type":"ASEMA 1-2 Klo 10.30-16"},{"name":"Broileri-fetapizzaa BBQ (A ,VL ,VS)\nRucolaa (G ,L ,M ,Veg)","price":"2,70 / 7,50 / 9,00","type":"ASEMA 1-2 Klo 16-20.00"},{"name":"PusPus-mousse (lakritsi&mansikka) L, A 1,50 € ()","price":"Hintaa ei annettu","type":"PÄIVÄN JÄLKIRUOKA"}]},{"name":"Macciavelli","url":"https://www.unica.fi/ravintolat/Yliopisto/Macciavelli/","openHours":"10.30-17.00","menu":[{"name":"Raastepihvejä (* ,A ,L ,M)\nRuohosipulikermaviilikastiketta (A ,G ,ILM ,L)\nPaahdettuja perunoita (* ,G ,ILM ,L ,M ,Veg)","price":"2,70 / 6,00 / 7,50 / 9,00","type":"KASVISLOUNAS"},{"name":"Chili con vege (* ,A ,ILM ,L ,M ,Veg ,VS)\nHöyrytettyä tummaa riisiä (* ,G ,L ,M ,Veg)","price":"2,70 / 6,00 / 7,50 / 9,00","type":"KASVISLOUNAS"},{"name":"Kebab-pastavuokaa (A ,L ,VS)","price":"2,70 / 6,00 / 7,50 / 9,00","type":"LOUNAS"},{"name":"Kuhapyöryköitä (A ,L ,M)\nTillikermaviilikastiketta (A ,G ,ILM ,L)\nKeitettyjä perunoita (* ,A ,G ,ILM ,L ,M ,Veg)","price":"2,70 / 6,00 / 7,50 / 9,00","type":"LOUNAS"},{"name":"Omena-mustikkakiisseliä & lakka-kauravaahtoa (A, G, VEG) ()","price":"1,50","type":"JÄLKKÄRI"}]},{"name":"Galilei","url":"https://www.unica.fi/ravintolat/Yliopisto/galilei/","openHours":"10.30 - 14.30","menu":[{"name":"Papu-linssicurryä (* ,G ,ILM ,L ,M ,Veg)\nHöyrytettyä tummaa riisiä (* ,G ,L ,M ,Veg)","price":"2,70 /7,50 / 9,00","type":"VEGAANINEN KASVISLOUNAS"},{"name":"TexMex-uunimakkaraa (A ,G ,L)\nSipulikastiketta (* ,A ,ILM ,L)\nKeitettyjä perunoita (* ,A ,G ,ILM ,L ,M ,Veg)","price":"2,70 /7,50 / 9,00","type":"LOUNAS"},{"name":"Savulohisalaatti (A ,G ,ILM ,L ,M)\nVärikästä pennepastaa (A ,ILM ,L ,M ,Veg)","price":"5,35 /7,50 / 9,00","type":"KAHVION SALAATTIBUFFA"},{"name":"Juustoinen juuressosekeitto (L, G, A, ILM) ()\nMaapähkinöitä (A ,G ,L ,M ,Veg)","price":"2,70 /7,50 / 9,00","type":"KAHVION KASVISKEITTO"},{"name":"Puolukkavispipuuroa (A ,L ,M ,Veg)","price":"1,80","type":"PÄIVÄN JÄLKIRUOKA"}]},{"name":"Monttu ja Mercatori","url":"https://www.unica.fi/ravintolat/Yliopisto/monttu-ja-mercatori/","openHours":"11:00-14:00","menu":[{"name":"Bataatti-maissipihvejä (* ,A ,G ,ILM ,L ,M ,VS)\nRuohosipulikermaviilikastiketta (A ,G ,ILM ,L)\nRyppyperunoita (* ,G ,ILM ,L ,M ,Veg)","price":"2,70/7,50/9,00","type":"Kasvislounas"},{"name":"Kalkkunaa salviakastikkeessa (* ,A ,G ,L)\nLuomutäysjyväkierrepastaa (* ,A ,ILM ,L ,M ,Veg)","price":"2,70/7,50/9,00","type":"Lounas"},{"name":"Paneroitu kampelafilee (* ,A ,L ,M)\nTillikermaviilikastiketta (A ,G ,ILM ,L)\nTillimuhennettu perunaa (A ,G ,L)\nKauden kasviksia (G ,L ,M ,Veg)","price":"5,35/9,90/10,50","type":"Deli lounas tarjolla klo 11.00 - 13.30"}]},{"name":"Dental","url":"https://www.unica.fi/ravintolat/Kupittaa/dental/","openHours":"10.45-13.30","menu":[{"name":"Peruna-kasviscurrya luomutofulla (* ,A ,G ,ILM ,L ,M ,Veg ,VS)","price":"2,70/7,50/9,00","type":"KASVISLOUNAS"},{"name":"Uunimakkaraa juustokuorrutteella (A ,G ,L)\nPerunasosetta (* ,A ,G ,ILM ,L)","price":"2,70/7,50/9,00","type":"KOTILOUNAS"},{"name":"Paneroitua broileria (G ,L ,M)\nBearnaisekastiketta (A ,G)","price":"5,35/10,50","type":"DELILOUNAS"}]},{"name":"Deli Pharma","url":"https://www.unica.fi/ravintolat/Kupittaa/deli-pharma/","openHours":null,"menu":[{"name":"Kasvispihvejä  A, L ()\nPaahdettuja lohkoperunoita (G ,ILM ,L ,M ,Veg)\nAvokado-kermaviilikastiketta (A ,G ,L)","price":"5,30 / 10,20","type":"BISTRO"},{"name":"Kirjolohta ja kasviksia inkiväärikastikkeessa (* ,A ,G ,ILM ,L ,M)\nBasmatiriisiä (G ,L ,M ,Veg)","price":"5,30 / 10,20","type":"BISTRO"},{"name":"Jauhelihalasagnea (A ,VS)","price":"5,30 / 10,20","type":"BISTRO"},{"name":"Vohveli hillolla ja kermavaahdolla A ()","price":"2,00","type":"JÄLKIRUOKA"}]},{"name":"Delica","url":"https://www.unica.fi/ravintolat/Kupittaa/delica/","openHours":"10:30-16:00","menu":[{"name":"Luomutofu-kasvishöystöä (* ,A ,G ,ILM ,L ,M ,Veg ,VS)\nHöyrytettyä tummaa riisiä (* ,G ,L ,M ,Veg)","price":"2,70 / 7,50  / 9,00","type":"KASVISLOUNAS"},{"name":"Kaali-jauhelihalaatikkoa (* ,G ,L ,M)\nPuolukkahilloa (G ,L ,M ,Veg)","price":"2,70 / 7,50 / 9,00","type":"LOUNAS"},{"name":"Paneroitua yrttikalaa (A ,ILM ,L ,M)\nSinappirelishkermaviilikastiketta (A ,G ,L)\nKeitettyjä luomuperunoita (* ,G ,ILM ,L ,M ,Veg)","price":"2,70 / 7,50  / 9,00","type":"LOUNAS"}]},{"name":"Linus","url":"https://www.unica.fi/ravintolat/Kupittaa/linus/","openHours":"10.30-13.30","menu":[{"name":"Peruna-kasviscurrya luomutofulla (* ,A ,G ,ILM ,L ,M ,Veg ,VS)","price":"2,70/7,50/9,00 €","type":"VEGAANINEN KASVISLOUNAS"},{"name":"Uunimakkaraa juustokuorrutteella (A ,G ,L)\nPerunasosetta (* ,A ,G ,ILM ,L)","price":"2,70/7,50/9,00 €","type":"KOTIRUOKALOUNAS"},{"name":"Teriyakimaustettua broileria (A ,G ,L ,M ,VS)","price":"2,70/7,50/9,00 €","type":"SALAATTILOUNAS"},{"name":"Paneroitua broileria (G ,L ,M)\nBearnaisekastiketta (A ,G)","price":"5,35/10,50 €","type":"DELILOUNAS"},{"name":"Omena-puolukkapiirakkaa (A ,L)\nVaniljakermavaahtoa (A ,G ,L)","price":"1,50 €","type":"JÄLKIRUOKA"}]},{"name":"Kisälli","url":"https://www.unica.fi/ravintolat/Kupittaa/kisalli/","openHours":"10.30-14.30 (bistro 10.30-13.30)","menu":[{"name":"Juurespihvejä (* ,A ,G ,ILM ,L ,M ,Veg)\nAurinkokuivatuilla tomaateilla maustettua majoneesia (A ,G ,ILM ,L ,M ,Veg)\nPaahdettuja lohkoperunoita (G ,ILM ,L ,M ,Veg)","price":"2,70 / 6,00 / 7,50 / 9,00","type":"ASEMA 1 / KASVISRUOKA"},{"name":"Kirjolohimurekepihvejä (A ,L)\nPaahdettuja lohkoperunoita (G ,ILM ,L ,M ,Veg)","price":"2,70 / 6,00 / 7,50 / 9,00","type":"ASEMA 1 / KOTIRUOKA"},{"name":"Kalkkunaa ja vihanneksia kookoskastikkeessa (* ,A ,G ,L ,M)\nHöyrytettyä tummaa riisiä (* ,G ,L ,M ,Veg)","price":"5,35 / 10,50","type":"BISTRO"},{"name":"Salaattiasemalla tarjolla runsas kattaus tuoreita kasviksia ja vihanneksia, sekä paljon erilaisia herkullisia lisukkeita. ()","price":"salaattiannokset alkaen 3,60€","type":"SALAATTIASEMA"},{"name":"Pannukakkua (A ,L)\nMansikkahilloa (G ,L ,M ,Veg)\nKermavaahtoa (A ,G ,L)","price":"1,50 / 1,80","type":"JÄLKIRUOKA"},{"name":"Kauden kasviksia (G ,L ,M ,Veg)\nPaahdettua broileria ja ratatouillea (A ,G ,L ,M ,VS)\nPapas arrugadas -perunoita (* ,G ,ILM ,L ,M ,Veg)","price":"12,00","type":"KAIVOMESTARIN LOUNAS"}]},{"name":"Sigyn","url":"https://www.unica.fi/ravintolat/taidekampus/Sigyn/","openHours":"11.00-14.00","menu":[{"name":"Peruna-kasviscurrya luomutofulla (* ,A ,G ,ILM ,L ,M ,Veg ,VS)\nHöyrytettyä tummaa riisiä (* ,G ,L ,M ,Veg)","price":"2,70 / 7,00 / 9,90","type":"KAHVILA & KELLARI"},{"name":"Pitakebab ja jogurttikastiketta (A ,L ,VS)\nRanskalaisia perunoita (G ,ILM ,L ,M ,Veg)","price":"5,35 / 7,00 / 9,90","type":"KAHVILA klo 11-14"},{"name":"Uunimakkaraa juustokuorrutteella (A ,G ,L)\nPerunasosetta (* ,A ,G ,ILM ,L)","price":"2,70 / 7,00 / 9,90","type":"KELLARI"},{"name":"Päivän jälkiruoka ()","price":"1,50- 3,00","type":"PÄIVÄN JÄLKIRUOKA"}]},{"name":"Unican Kulma","url":"https://www.unica.fi/ravintolat/Muut/unican-kulma/","openHours":"11:00-14:30","menu":[{"name":"Peruna-kasviscurrya luomutofulla (* ,A ,G ,ILM ,L ,M ,Veg ,VS)","price":"2,70/9,90","type":"Kulman vegaaninen kasvislounas"},{"name":"Uunimakkaraa juustokuorrutteella (A ,G ,L)\nPerunasosetta (* ,A ,G ,ILM ,L)","price":"2,70/9,90","type":"Kulman lounas"},{"name":"Paneroitua broileria (G ,L ,M)\nBearnaisekastiketta (A ,G)","price":"5,35/11,00","type":"KULMAN  DELI LOUNAS"}]},{"name":"Kasvisravintola Piccu Maccia","url":"https://www.unica.fi/ravintolat/Muut/piccu-maccia/","openHours":"11.00-14.30","menu":[{"name":"Kauden salaattisekoitusta (G ,L ,M ,Veg)\nTomaattihilloketta (A ,G ,L ,M ,Veg)\nPorkkanahummusta (* ,A ,G ,L ,M ,Veg ,VS)\nLime-kookoskermasmoothie (A ,G ,L)\nPunajuuri-inkiväärishotti (G ,L ,M ,Veg)\nKimchi-kaalisalaattia (G ,L ,M ,Veg ,VS)\nMaissi-lehtikaalisalaattia (A, VEG) ()\nPapu-herkkusieni-maissisalaattia (A, G, VEG) ()\nHärkis-pastasalaattia (A, VEG) ()\nKukkakaalisalaattia (A, G, VEG) ()\nCantaloupe melonia (A, G, VEG) ()\nProteiinilisät; Kasvispyöryköitä (A, G, M) & \"Sticky Bites\" Soijaa (A, G, VEG) ()","price":"5,35 / 9,40 / 9,40 / 10,50","type":"GREEN BUFFET - sis. lämpimän kasvislisäkkeen ja keiton"},{"name":"Kauden kasviksia (G ,L ,M ,Veg)","price":"Hintaa ei annettu","type":"LÄMMIN KASVISLISÄKE (Green Buffet)"},{"name":"Parsakaalisosekeittoa (* ,A ,G ,ILM ,L ,M ,Veg)\nTortilla-chipsejä (G ,L ,M ,Veg)","price":"2,70 / 6,00 / 7,50 / 9,00","type":"KASVISKEITTO (sisältyy Green buffettiin)"},{"name":"Halloum-rucola-uunipastaa (A ,VS)","price":"5,35 / 9,40 / 9,40 / 10,50","type":"G R E E N  D E L I #1 sis. side salaatin"},{"name":"Chilipaahdettua kirjolohta (* ,A ,G ,L ,M)\nBBQ-kastiketta (* ,A ,G ,L ,M)\nPorkkana-perunasosetta (A ,G ,ILM ,L)","price":"5,35 / 9,40 / 9,40 / 10,50","type":"D E L I #2 sis. side salaatin"}]},{"name":"Flavoria","url":"https://www.sodexo.fi/ravintolat/flavoria-medisiina-d","openHours":"Lounas MA-PE 10:30-13:30\nKahvila MA-TO 07:30-15:30\nKahvila PE 07:30-14:30","menu":[{"name":"Punajuuri-spelttipihvit, piparjuurimajoneesia ja perunaa","price":"2,70 € / 8,35 €","type":"FROM THE FIELD-VEGAN"},{"name":"Naudanlihaa ja kasviksia korealaiseen tapaan ja riisiä","price":"2,70 € / 8,35 €","type":"FROM OUR FAVORITES 2"},{"name":"Juustokuorrutettua uunimakkaraa ja perunamuusia","price":"2,70 € / 8,35 €","type":"FROM OUR FAVORITES 1"},{"name":"Aurajuustosalaatti","price":"2,70 € / 7,30 €","type":"FROM THE GARDEN (kahvilasta)"},{"name":"Mozzarella patonki","price":"2,70 € / 7,30 €","type":"FROM OUR BAKERY (kahvilasta)"},{"name":"Poke bowl lohi","price":"5,35 € / 9,80 €","type":"FROM THE KITCHEN (grillistä)"}]}]