[{"name":"Aurum","url":"https://www.karkafeerna.fi/fi/lounas","openHours":"SULJETTU 23.6.-14.8.","menu":[{"name":"Kanankoipireisi ja currykastiketta, riisi ","price":"2,70€","type":"Lounas"},{"name":"Pasta Bolognese ","price":"2,70€","type":"Lounas"},{"name":"Soija-Bolognese ","price":"2,70€","type":"Vegaaninen"},{"name":"Porkkana-inkeväärisoseekeitto, paahdetut siemenet ","price":"2,40€","type":"Vegaaninen"}]},{"name":"Aurum Bistro","url":"https://www.karkafeerna.fi/fi/lounas","openHours":"Ei lounasta tänään","menu":[]},{"name":"Kåren","url":"https://www.karkafeerna.fi/fi/lounas","openHours":"Ei lounasta tänään","menu":[]},{"name":"Arken","url":"https://www.karkafeerna.fi/fi/lounas","openHours":"Ei lounasta tänään","menu":[]},{"name":"ASA","url":"https://www.karkafeerna.fi/fi/lounas","openHours":"Ei lounasta tänään","menu":[]},{"name":"Assarin Ullakko","url":"https://www.unica.fi/ravintolat/Yliopisto/assarin-ullakko/","openHours":"11.00-17.45","menu":[{"name":"Kasvis-herkkusienikiusausta (* ,A ,G ,ILM ,L ,VS)","price":"2,70 / 7,00 / 8,10","type":"ASEMA 1-2"},{"name":"Kikherne-kukkakaalicurrya (* ,G ,ILM ,L ,M ,Veg ,VS)","price":"2,70 / 7,00 / 8,10","type":"VEGAANINEN LOUNAS"},{"name":"Naudanlihapataa meksikolaisittain *,M, G, A ()","price":"2,70 / 7,00 / 8,10","type":"ASEMA 1-2"},{"name":"Kermaista kirjolohikeittoa sis. keittojuureksia (A ,G ,ILM ,L)","price":"2,70 / 7,00 / 8,10","type":"ASEMA 1-2"}]},{"name":"Macciavelli","url":"https://www.unica.fi/ravintolat/Yliopisto/Macciavelli/","openHours":"10.30-15.00","menu":[{"name":"Jauheliha-pennepastaa (* ,A ,L ,M)","price":"2,70 / 5,80 / 7,00 / 8,10","type":"LOUNAS"},{"name":"Rapeita kalapaloja (* ,A ,L ,M)\nRuohosipulikermaviilikastiketta (A ,G ,ILM ,L)\nKeitettyjä perunoita (* ,A ,G ,ILM ,L ,M ,Veg)","price":"2,70 / 5,80 / 7,00 / 8,10","type":"LOUNAS"},{"name":"Kaurakeksi-Nutellarahkaa (A, L) ()","price":"Hintaa ei annettu","type":"JÄLKKÄRI"}]},{"name":"Galilei","url":"https://www.unica.fi/ravintolat/Yliopisto/galilei/","openHours":"Ei lounasta tänään","menu":[]},{"name":"Monttu ja Mercatori","url":"https://www.unica.fi/ravintolat/Yliopisto/monttu-ja-mercatori/","openHours":"Ei lounasta tänään","menu":[]},{"name":"Dental","url":"https://www.unica.fi/ravintolat/Kupittaa/dental/","openHours":"10.45-13.30","menu":[{"name":"Kasviskroketteja (G ,ILM ,L ,M ,Veg ,VS)\nPico de gallo -linssisalsaa (* ,A ,ILM ,L ,M ,Veg ,VS)\nPapas arrugadas -perunoita (* ,G ,ILM ,L ,M ,Veg)","price":"2,70/7,50/9,00","type":"KASVISLOUNAS"},{"name":"Lihapyörykät cajunkastikkeessa (L) ()\nPerunasosetta (G,L) ()","price":"2,70/7,50/9,00","type":"KOTILOUNAS"}]},{"name":"Deli Pharma","url":"https://www.unica.fi/ravintolat/Kupittaa/deli-pharma/","openHours":null,"menu":[{"name":"Ratatouillea (* ,A ,G ,ILM ,L ,M ,Veg ,VS)\nPaahdettuja auringonkukansiemeniä (G ,L ,M ,Veg)","price":"2,70 / 7,00 / 8,10","type":"Vege Bistro"},{"name":"Jauhelihapyöryköitä (* ,A ,L ,M)\nPerunasosetta (* ,A ,G ,ILM ,L)\nRuskeaa kastiketta (* ,A ,ILM ,L ,M)","price":"2,70 / 7,00 / 8,10","type":"Bistro"},{"name":"Porsaanfileepihvi italialaisittain (A ,G ,L ,M ,VS)\nPariisinperunoita (A ,G ,ILM ,L ,M ,Veg)\nKaramellisoituja porkkanoita (A ,G ,L)","price":"5,30  / 10,20","type":"Bistro"},{"name":"Vohveleita (A)\nMansikkahilloa (G ,L ,M ,Veg)\nVaniljakermavaahtoa (A ,G ,L)","price":"2,00","type":"JÄLKIRUOKA"}]},{"name":"Delica","url":"https://www.unica.fi/ravintolat/Kupittaa/delica/","openHours":"10:30-16:00","menu":[{"name":"Ratatouillea (* ,A ,G ,ILM ,L ,M ,Veg ,VS)\nPaahdettuja auringonkukansiemeniä (G ,L ,M ,Veg)","price":"2,70 / 7,00 / 8,10","type":"KASVISLOUNAS"},{"name":"Jauhelihapyöryköitä (* ,A ,L ,M)\nPerunasosetta (* ,A ,G ,ILM ,L)\nRuskeaa kastiketta (* ,A ,ILM ,L ,M)","price":"2,70 / 7,00/ 8,10","type":"LOUNAS"},{"name":"Porsaanfileepihvi italialaisittain (A ,G ,L ,M ,VS)\nPariisinperunoita (A ,G ,ILM ,L ,M ,Veg)\nKaramellisoituja porkkanoita (A ,G ,L)","price":"5,30 / 10,20","type":"LOUNAS"},{"name":"Vohveleita (A)\nMansikkahilloa (G ,L ,M ,Veg)\nVaniljakermavaahtoa (A ,G ,L)","price":"2,00","type":"JÄLKIRUOKA"}]},{"name":"Linus","url":"https://www.unica.fi/ravintolat/Kupittaa/linus/","openHours":"10.30-13.30","menu":[{"name":"Kasviskroketteja (G ,ILM ,L ,M ,Veg ,VS)\nPico de gallo -linssisalsaa (* ,A ,ILM ,L ,M ,Veg ,VS)\nPapas arrugadas -perunoita (* ,G ,ILM ,L ,M ,Veg)","price":"2,70/7,50/9,00 €","type":"VEGAANINEN KASVISLOUNAS"},{"name":"Rapeita kalapaloja (* ,A ,L ,M)\nRuohosipulikermaviilikastiketta (A ,G ,ILM ,L)\nPerunasosetta (* ,A ,G ,ILM ,L)","price":"2,70/7,50/9,00 €","type":"KOTIRUOKALOUNAS"},{"name":"Teriyakimaustettua broileria (A ,G ,L ,M ,VS)","price":"2,70/7,50/9,00 €","type":"SALAATTILOUNAS"},{"name":"Kassleria cajunkastikkeessa (A ,G ,L ,VS)\nPaahdettuja perunoita (G ,ILM ,L ,M ,Veg)","price":"5,35/10,50 €","type":"DELILOUNAS"},{"name":"Paahdettua kaalia ja porkkanaa (G ,L ,M ,Veg)","price":"Hintaa ei annettu","type":"Lounas"},{"name":"Mansikka-banaanismoothie (*, G, L, M, Veg.) ()","price":"1,50 €","type":"JÄLKIRUOKA"}]},{"name":"Kisälli","url":"https://www.unica.fi/ravintolat/Kupittaa/kisalli/","openHours":"10.30-14.00","menu":[{"name":"Juurespihvejä (* ,A ,G ,ILM ,L ,M ,Veg)\nTomaattisalsaa (A ,G ,ILM ,L ,M ,Veg)\nPapas arrugadas -perunoita (* ,G ,ILM ,L ,M ,Veg)","price":"2,70 / 6,00 / 7,50 / 9,00","type":"ASEMA 1 / KASVISRUOKA"},{"name":"Jauhelihapyörykkä (A,L,M) ja rosepippurikastiketta (A,L,G) ()\nPerunasose (L,G) ()","price":"2,70 / 6,00 / 7,50 / 9,00","type":"ASEMA 1 / KOTIRUOKA"},{"name":"Paahdettua broileria gruusialaisittain (A ,G ,L ,VS)\nKauden kasviksia (G ,L ,M ,Veg)\nPapas arrugadas -perunoita (* ,G ,ILM ,L ,M ,Veg)","price":"5,35 / 10,50","type":"BISTRO"},{"name":"Mustaherukkakiisseliä (G ,L ,M ,Veg)\nMarianne-kermavaahtoa (A ,VL)","price":"1,50 / 1,80","type":"JÄLKIRUOKA"}]},{"name":"Sigyn","url":"https://www.unica.fi/ravintolat/taidekampus/Sigyn/","openHours":"11.00-14.00","menu":[{"name":"Kikherne-bataattipataa (* ,A ,G ,ILM ,L ,M ,Veg ,VS)\nHöyrytettyä tummaa riisiä (* ,G ,L ,M ,Veg)","price":"2,70 / 7,00 / 9,90","type":"KAHVILA & KELLARI"},{"name":"Kassleria cajunkastikkeessa (A ,G ,L ,VS)\nPaahdettuja perunoita (G ,ILM ,L ,M ,Veg)","price":"5,35 / 7,00 / 9,90","type":"KAHVILA klo 11-14"},{"name":"Savuporokiusausta (* ,A ,G ,ILM ,L)","price":"2,70 / 7,00 / 9,90","type":"KELLARI"},{"name":"Marjamysliä ()","price":"1,50- 3,00","type":"PÄIVÄN JÄLKIRUOKA"}]},{"name":"Unican Kulma","url":"https://www.unica.fi/ravintolat/Muut/unican-kulma/","openHours":"11:00-14:30","menu":[{"name":"Kasviskroketteja (G ,ILM ,L ,M ,Veg ,VS)\nPico de gallo -linssisalsaa (* ,A ,ILM ,L ,M ,Veg ,VS)\nPapas arrugadas -perunoita (* ,G ,ILM ,L ,M ,Veg)","price":"2,70/8,90","type":"Kulman vegaaninen kasvislounas"},{"name":"Päivän salaatti ()","price":"5.35/9,50","type":"Kulman salaatti"},{"name":"Savuporokiusaus (G,L) ()","price":"2,70/8,90","type":"Kulman lounas"}]},{"name":"Kasvisravintola Piccu Maccia","url":"https://www.unica.fi/ravintolat/Muut/piccu-maccia/","openHours":"Ei lounasta tänään","menu":[]},{"name":"Flavoria","url":"https://www.sodexo.fi/ravintolat/flavoria-medisiina-d","openHours":"Lounas MA-PE 10:30-13:30\nKahvila MA-TO 07:30-15:30\nKahvila PE 07:30-14:30","menu":[{"name":"Papu-pähkinätaginea ja paahdettua perunaa","price":"2,70 € / 8,35 €","type":"FROM THE FIELD-VEGAN"},{"name":"Broilerilasagnettea","price":"2,70 € / 8,35 €","type":"FROM OUR FAVORITES 2"},{"name":"Fetatortillat, salsaa ja ranskankermaa","price":"2,70 € / 8,35 €","type":"FROM OUR FAVORITES 1"},{"name":"Blue Cheese burger ja ranskalaiset perunat","price":"5,35 € / 9,80 €","type":"FROM THE KITCHEN (grillistä)"},{"name":"Lounaspatonki tomaatti-mozzarellatäytteellä","price":"2,70 € / 7,30 €","type":"FROM OUR BAKERY (kahvilasta)"},{"name":"Broiler Caesarsalaattia","price":"2,70 € / 7,30 €","type":"FROM THE GARDEN (kahvilasta)"},{"name":"Suklaakääretorttua","price":"1,80 €","type":"FROM THE SWEET"}]}]