[{"name":"Arken","url":"https://www.karkafeerna.fi/fi/lounas","openHours":"MA-TO 8-15.30\n(LOUNAS 11-15)\nPE 8-15\n(LOUNAS 11-14.30)","menu":[{"name":"Lohiwokkia nuudeleilla ja Hoisinkastikkeella ","price":"2,95€","type":"Lounas"},{"name":"Vegaaninen falafelihampurilainen chilimajoneesilla ja paahdetuilla perunoilla ","price":"2,95€","type":"Vegaaninen"},{"name":"Arken patonki (Klo. 10 alkaen) Kana, Mozzarella, Falafel ","price":"2,95€","type":"Lounas"}]},{"name":"ASA","url":"https://www.karkafeerna.fi/fi/lounas","openHours":"MA-PE 9-14\n(LOUNAS 11-14)","menu":[{"name":"AS(I)A Ramen Soup Bowl(Beef Brisket in soy & ginger/ Seitan in Soy & ginger) ","price":"4,25 - 15,00€","type":"Lounas"},{"name":"Hampurilainen ja kurkkumajoneesia  ","price":"2,95€","type":"Lounas"},{"name":"Mustapapu-hampurilainen ja paprikamajoneesi ","price":"2,95€","type":"Vegaaninen"},{"name":"Panini (Klo. 10 alkaen)  ","price":"2,95€","type":"Lounas"}]},{"name":"Aurum","url":"https://www.karkafeerna.fi/fi/lounas","openHours":"MA-TO 7.30-18.00\n(LOUNAS 10.30-18.00)\nPE 7.30-14.30\n(LOUNAS 10.30-14.00)\nLA 12-15 ","menu":[{"name":"Kanankoipireisi ja currykastiketta, kaurariisi ","price":"2,95€","type":"Lounas"},{"name":"Papupyörykät ja pinaattikastiketta, perunat ","price":"2,95€","type":"Vegaaninen"},{"name":"Vegaani gulassikeitto härkäpavuilla ","price":"2,95€","type":"Vegaaninen"}]},{"name":"Aurum Bistro","url":"https://www.karkafeerna.fi/fi/lounas","openHours":"MA-PE 11-14","menu":[{"name":"Caesarsalaatti ","price":"4,25 - 15,00€","type":"Lounas"},{"name":"Lohi Sandefjordin kastikkeella ","price":"4,25 - 15,00€","type":"Lounas"},{"name":"Kanafile ja yrttimajoneesi ","price":"4,25 - 15,00€","type":"Lounas"},{"name":"Ribs aiolilla ","price":"4,25 - 15,00€","type":"Lounas"},{"name":"Aurumin pekonihampurilainen (Nauta) ","price":"4,25 - 15,00€","type":"Lounas"},{"name":"Mustapapuburgeri ","price":"4,25 - 15,00€","type":"Vegaaninen"},{"name":"Loaded fries ","price":"4,25 - 15,00€","type":"Kasvis"}]},{"name":"Kåren","url":"https://www.karkafeerna.fi/fi/lounas","openHours":"MA-PE 11-14","menu":[{"name":"Juustokuorutettua uunimakkaraa bbq-tomaattikastikkeella, paistetut perunat ","price":"2,95€","type":"Lounas"},{"name":"Vegaaninen pyttipannu savutofulla ja paprikamajoneesilla ","price":"2,95€","type":"Vegaaninen"},{"name":"Saalaattikulho Halloumilla tai broilerilla ","price":"2,95€","type":"Kasvis"},{"name":"Porkkana-inkiväärisosekeitto, raejuustoa ","price":"2,95€","type":"Kasvis"}]},{"name":"Assarin Ullakko","url":"https://www.unica.fi/ravintolat/Yliopisto/assarin-ullakko/","openHours":"10.30-19.45","menu":[{"name":"Tulisen makeaa Kung Po-broileripataa (*, A, G, ILM, L, M, VS)","price":"2,95 / 7,70 / 9,20","type":"ASEMA 1-2 10:30-19:45"},{"name":"Kotimaisia kirjolohipyöryköitä (A, ILM, L)\nRuohosipuli-tillijogurttia (A, G, ILM, L)","price":"2,95 / 7,70 / 9,20","type":"ASEMA 1-2  10:30-16:00"},{"name":"Talon mausteista kurpitsalasagnea (A, ILM, L)","price":"2,95 / 7,70 / 9,20","type":"BRYGGE 10:30-15:00"},{"name":"Paneroituja porkkanapihvejä (A, G, ILM, L, M, Veg)\nPersiljagurttia (A, ILM, L, M, Veg)","price":"2,95 / 7,70 / 9,20","type":"VEGAANINEN LOUNAS"},{"name":"Välimerellistä fetajuusto-paprikapannupizzaa (A, L)","price":"2,95  / 7,70 / 9,20","type":"ASEMA 1-2  11.00-15.00"},{"name":"Rapea kalaleike juustotäytteellä (A, ILM, VL)\nSambal Oelek -jogurttia (*, A, G, ILM, L)","price":"2,95 / 7,70 / 9,20","type":"ASEMA 1-2 16:00-19:45"},{"name":"Täysjyväohraa (*, A, ILM, L, M, Veg)\nSmoked paprika -paahdettuja perunoita (*, G, ILM, L, M, Veg, VS)","price":"Hintaa ei annettu","type":"LÄMPIMÄT LISUKKEET"}]},{"name":"Macciavelli","url":"https://www.unica.fi/ravintolat/Yliopisto/Macciavelli/","openHours":"10.30-17.00","menu":[{"name":"Talon kasvislasagnettea (A, ILM, L)","price":"2,95 / 6,50 / 7,70 / 9,20","type":"KASVISLOUNAS"},{"name":"Kasvispuikkoja (A, ILM, L, M, Veg)\nPiparjuurimajoneesia (A, G, ILM, L, M, Veg)\nPaahdettua perunaa ja juureksia \t(*, G, ILM, L, M, Veg) ()","price":"2,95 / 6,50 / 7,70 / 9,20","type":"KASVISLOUNAS"},{"name":"Kalapihvejä kotimaisesta kalasta (A, ILM, L)\nKananmuna-tillikastiketta (*, A, L)\nPaahdettua perunaa ja juureksia (*, G, ILM, L, M, Veg)","price":"2,95 / 6,50 / 7,70 / 9,20","type":"LOUNAS"},{"name":"Broilericurrya (A, G, ILM, L)\nKotimaista kauraa & porkkanaa (*, A, G, ILM, L, M, Veg)","price":"2,95 / 6,50 / 7,70 / 9,20","type":"LOUNAS"},{"name":"Pyttipannua (A, G, L, M) ()","price":"2,95 / 6,50 / 7,70 / 9,20","type":"LOUNAS"},{"name":"Appelsiinikääretorttua (A, L) ()","price":"1,50","type":"JÄLKIRUOKA"}]},{"name":"Galilei","url":"https://www.unica.fi/ravintolat/Yliopisto/galilei/","openHours":"10.30 - 14.30","menu":[{"name":"Falafel HotDog, punakaalia, rapeaa sipulia & chilimajoneesia (A, ILM, L, M, Veg, VS)","price":"2,95 /7,70 / 9,20","type":"VEGAANINEN KASVISLOUNAS"},{"name":"Savulohipastaa (*, A, ILM, L) ()","price":"2,95 /7,70 / 9,20","type":"LOUNAS"},{"name":"Paahdettua kirjolohta (*, A, G, ILM, L, M)\nLimemajoneesia (*, A, G, ILM, L, M) ()","price":"5,60/9,90/10,70","type":"PÄIVÄN LOHI"},{"name":"Juustoista juuressosekeittoa (*, A, G, ILM, L)","price":"2,95 /7,70 / 9,20","type":"KAHVION KASVISKEITTO TARJOLLA 10.30-13.30"},{"name":"Tarjolla laaja valikoima tuoreita kasviksia ja proteiineja. ()","price":"2,2€/100g","type":"KAHVION SALAATTIASEMA TARJOLLA 10.30-13.30"},{"name":"Kauraa ja kasviksia (A, G, ILM, L, M, Veg)\nPaahdettuja perunoita (*, A, G, ILM, L, M, Veg)\nKestivihanneksia (G, L, M, Veg)","price":"Hintaa ei annettu","type":"LÄMPIMÄT LISÄKKEET"},{"name":"Mustikkarahkaa (L, G) ()","price":"1,80","type":"JÄLKIRUOKA"}]},{"name":"Monttu ja Mercatori","url":"https://www.unica.fi/ravintolat/Yliopisto/monttu-ja-mercatori/","openHours":"11:00-13:00","menu":[{"name":"Väimerellistä kasvis-fetajuustopataa (*, A, G, ILM, L)","price":"2,95/7,70/9,20","type":"Kasvislounas"},{"name":"Kotimaisia kalapyöryköitä (A, ILM, L)\nTillijogurttia (*, A, G, ILM, L)","price":"2,95/7,70/9,20","type":"Lounas"},{"name":"Kotimaista kauraa & porkkanaa (*, A, G, ILM, L, M, Veg)\nPerunamuusia (*, A, G, ILM, L)\nSatokauden kasviksia (G, L, M, Veg)","price":"Hintaa ei annettu","type":"Lämpimät lisäkkeet"}]},{"name":"Dental","url":"https://www.unica.fi/ravintolat/Kupittaa/dental/","openHours":"10.45- 13.30","menu":[{"name":"Kikherne-bataattipataa (*, A, G, ILM, L, M, Veg, VS)","price":"2,95/7,70/9,20 €","type":"KASVISLOUNAS"},{"name":"Kalkkunaa rakuunakastikkeessa (*, A, G, L)","price":"2,95/7,70/9,20 €","type":"KOTILOUNAS 1"},{"name":"Rosmariini paahdettua broilerinfileetä (*, G, L, M)\nPunaviinikastiketta (G, L, M, VS)\nPaahdettua perunaa ja juureksia (*, G, ILM, L, M, Veg)","price":"5,60/10,70 €","type":"DELILOUNAS"}]},{"name":"Deli Pharma","url":"https://www.unica.fi/ravintolat/Kupittaa/deli-pharma/","openHours":"10:30-14:00","menu":[{"name":"Punajuuri-vuohenjuustolasagnea ja lehtipinaattia (A, VL, VS)","price":"5,60 / 10,70 / 13,40 (buffet)","type":"KASVISBISTRO"},{"name":"Pulled pork-bearnaisepizza (A, L)","price":"5,60 / 10,70 / 13,40 (buffet)","type":"BISTRO1"},{"name":"Paahdettua kirjolohta (*, A, G, ILM, L, M)\nHollandaisea (A, G, L)\nPerunasosetta (A, G, L)","price":"5,60 / 10,70 / 13,40 (buffet)","type":"BISTRO"},{"name":"Karamellisoituja porkkanoita (A, G, L)","price":"Hintaa ei annettu","type":"LÄMMIN KASVISLISUKE"},{"name":"Suklaa-vadelmamoussea (A,G) ()","price":"1,80","type":"JÄLKIRUOKA"}]},{"name":"Delica","url":"https://www.unica.fi/ravintolat/Kupittaa/delica/","openHours":"10:30-18.00","menu":[{"name":"Paneroituja porkkanapihvejä (A, G, ILM, L, M, Veg)\nChiligurttia (*, A, G, ILM, L, M, Veg)\nTummaa riisiä (*, G, L, M, Veg)","price":"2,95 / 9,20","type":"KASVISLOUNAS"},{"name":"Porsasta ja kasviksia Sweet & Sour (*, A, L, M)\nTummaa riisiä (*, G, L, M, Veg)","price":"2,95 / 9,20","type":"KOTILOUNAS"},{"name":"Jauhelihapyöryköitä (*, A, L, M)\nPippurikastiketta (*, A, ILM, L)\nKeitettyjä perunoita (*, A, G, ILM, L, M, Veg)","price":"2,95 / 9,20","type":"KOTILOUNAS1"},{"name":"Tacoja (G, L, M, Veg)\nBroileri-kasvistäytettä (A, G, L, M, VS)\nSmetanaa (A, G, ILM, L)","price":"2,95 / 9,20","type":"MYÖHÄINEN LOUNAS KLO 14-18"}]},{"name":"Linus","url":"https://www.unica.fi/ravintolat/Kupittaa/linus/","openHours":"10.30-13.30","menu":[{"name":"Kikherne-bataattipataa (*, A, G, ILM, L, M, Veg, VS)\nTummaa riisiä (*, G, L, M, Veg)","price":"2,95/7,70/9,20 €","type":"KASVISLOUNAS"},{"name":"Kalkkunaa rakuunakastikkeessa (*, A, G, L)\nTummaa riisiä (*, G, L, M, Veg)","price":"2,95/7,70/9,20 €","type":"KOTIRUOKALOUNAS"},{"name":"Rosmariini paahdettua broilerinfileetä (*, G, L, M)\nPunaviinikastiketta (G, L, M, VS)\nPaahdettua perunaa ja juureksia (*, G, ILM, L, M, Veg)","price":"5,60/10,70 €","type":"DELILOUNAS Tarjolla 10.30-13.00 Linja 3"},{"name":"Mustaherukkarahkaa (A, G, L)","price":"1,50 €","type":"JÄLKIRUOKA"}]},{"name":"Kisälli","url":"https://www.unica.fi/ravintolat/Kupittaa/kisalli/","openHours":"10.30-14.30","menu":[{"name":"Juures-voipapupyöryköitä\n (*, A, G, L, M, Veg)\nLimellä maustettua kurkku-kauragurttia\n (*, A, ILM, L, M, Veg, VS)\nPaahdettua perunaa (*, G, ILM, L, M, Veg)","price":"2,95 / 6,50 / 7,70 / 9,20","type":"ASEMA 1 / KASVISRUOKA (tarjolla ma-to 10.30-14.30, pe 10.30-14)"},{"name":"Kinkkukiusausta (*, A, G, ILM, L)","price":"2,95 / 6,50 / 7,70 / 9,20","type":"ASEMA 1 / KOTIRUOKA  (tarjolla ma-to 10.30-14.30, pe 10.30-14)"},{"name":"Sataymaustettua broileria (A, G, L, M, VS)\nBasmatia (G, L, M, Veg)","price":"5,60 / 10,70","type":"BISTRO (tarjolla klo ma-to 10.30-13.00, pe 10.30-12.30)"},{"name":"Tarjolla laaja valikoima tuoreita kasviksia ja proteiineja. ()","price":"2,30 €/100 g","type":"SALAATTIASEMA (tarjolla klo ma-to 10.30-13.00, pe 10.30-12.30)"},{"name":"Suklaamoussea (A, G, L)","price":"1,50 / 1,80","type":"JÄLKIRUOKA"},{"name":"Paprikalla maustettuja lammaspihvejä\n (A, L, M, VS)\nMinttujogurttikastiketta (A, G, L)\nAnnanperunoita (A, G, L)","price":"12,20","type":"KAIVOMESTARIN LOUNAS (tarjolla ma-to 11.00-14.00, pe 11-13.30)"}]},{"name":"Sigyn","url":"https://www.unica.fi/ravintolat/taidekampus/Sigyn/","openHours":"11.00-14.00","menu":[{"name":"Koskenlaskija-härkislasagnea (A, ILM, L, VS) ()","price":"2,95 / 7,70 / 10,10","type":"Kasvisruoka (tarjoillaan kahvilassa)"},{"name":"Kasvisbolognesea (*, A, G, ILM, L, M, Veg)\nLuomutäysjyväpastaa (*, A, ILM, L, M, Veg)","price":"2,95 / 7,70 / 10,10","type":"Vegaaninen lounas"},{"name":"Kalapyöryköitä (*, A, G, ILM, L, M)\nTartarjogurttia (*, A, G, L)\nKeitettyjä perunoita (*, A, G, ILM, L, M, Veg)","price":"2,95  / 7,70 / 10,10","type":"Kotiruoka2"}]},{"name":"Unican Kulma","url":"https://www.unica.fi/ravintolat/Muut/unican-kulma/","openHours":"11:00-19:00","menu":[{"name":"Kikherne-bataattipataa (*, A, G, ILM, L, M, Veg, VS)\nTummaa riisiä (*, G, L, M, Veg)","price":"2,95/10,10","type":"LOUNAS"},{"name":"Kalkkunaa rakuunakastikkeessa (*, A, G, L)\nTummaa riisiä (*, G, L, M, Veg)","price":"2,95/10,10","type":"LOUNAS"},{"name":"Rosmariini paahdettua broilerinfileetä (*, G, L, M)\nPunaviinikastiketta (G, L, M, VS)\nPaahdettua perunaa ja juureksia (*, G, ILM, L, M, Veg)","price":"5,60/13,20","type":"KULMAN  DELI LOUNAS"}]},{"name":"Kasvisravintola Piccu Maccia","url":"https://www.unica.fi/ravintolat/Muut/piccu-maccia/","openHours":"10.30-14.00","menu":[{"name":"Mustikka-rosmariinishotti (A, G, VEG) ()\nPaahdettua lehtikaalia (A, G, VEG) ()\nPikkelöityä fenkolia ja punasipulia (A, G, VEG) ()\nKotimaisia omenoita (A, G, VEG) ()\nKotijuustoa (A, G, L) ()\nYrttimaustettua nyhtökauraa (A, G, VEG) ()\nKeittiön tervehdys: sienisalaattia (A, G, L) ()\nMustapapu-luomuohraseosta (A, L, M, Veg)\nPaprika-kurkkusalaattia (G, L, M, Veg)\nPaahdettua palsternakkaa (G, L, M, Veg)\nKauden salaattisekoitusta (G, L, M, Veg)\nKaalipiirakkaa (A, L)\nPaprika-sipulilisäkettä (*, G, L, M, Veg)\nPikkelöityjä vihanneksia (*, G, L, M, Veg)\nPeruna-linssisalaattia (A, L)\nPunajuuri-saksanpähkinähummusta (A, G, L, M, Veg, VS)\nJuustoista curry-yrttilevitettä (A, G, L)\nPaahdettua valkosipulia (G, L, M, Veg, VS)\nPaahdettua parsakaalia (G, L, M, Veg)","price":"5,60 / 10,70 / 10,70 / 10,70","type":"GREEN BUFFET - sis. lämpimän kasvislisäkkeen ja keiton"},{"name":"Kukkakaalisosekeittoa (*, A, G, ILM, L, M, Veg)\nPaahdettuja auringonkukansiemeniä ()","price":"2,95 / 6,50 / 7,70 / 9,20","type":"KASVISKEITTO (sisältyy Green buffettiin)"},{"name":"Satokauden kasviksia (G, L, M, Veg)","price":"Hintaa ei annettu","type":"LÄMMIN KASVISLISÄKE (sisältyy Green buffettiin)"},{"name":"Ruis-kasvishamppari, salaattia, tomaattia, kauragurttia,paahdettuja uuniperunalohkoja (A, ILM, L) ()","price":"5,60 / 10,70 / 10,70 / 10,70","type":"G R E E N  D E L I #1 sis. side salaatin"},{"name":"Paahdettua kirjolohta, tilli-ruohosipulikauragurttia, paahdettuja juureksia, höyrypottua (A, ILM, G, L) ()","price":"5,60 / 10,70 / 10,70 / 10,70","type":"D E L I # 2 sis. side salaatin # 2"}]},{"name":"Flavoria","url":"https://www.sodexo.fi/ravintolat/flavoria-medisiina-d","openHours":"Lounas MA-PE 10:30-13:30\nKahvila MA-TO 07:30-15:30\nKahvila PE 07:30-14:30","menu":[{"name":"Falafel pita ja hummusta","price":"2,95 € / 9,35 €","type":"FROM THE FIELD-VEGAN"},{"name":"Broileria makeassa soijakastikkeessa ja basmatiriisiä","price":"2,95 € / 9,35 €","type":"From our favorites 1"},{"name":"Lohikeittoa","price":"2,95 € / 9,35 €","type":"From our favorites 2"},{"name":"Paahdettua paprikakeittoa (hinta sisältää 1-2 napasannosta)","price":"2,95 € / 8,30 €","type":"FROM THE SOUP BOWL"},{"name":"Päivän patonki: Tomaatti- Mozzarella ","price":"2,95 € / 7,80 €","type":"FROM OUR BAKERY (kahvilasta)"},{"name":"Kreikkalainen salaatti","price":"2,95 € / 8,30 €","type":"FROM THE GARDEN (kahvilasta)"},{"name":"Blue cheese burger ja bataattiranskalaiset","price":"5,60 € / 10,90 €","type":"FROM THE KITCHEN (grillistä)"}]}]