[{"name":"Arken","url":"https://www.karkafeerna.fi/fi/lounas","openHours":"SULJETTU 20.12-6.1","menu":[{"name":"Hyvää Joulua! ","price":"Hintaa ei annettu","type":"Lounas"}]},{"name":"ASA","url":"https://www.karkafeerna.fi/fi/lounas","openHours":"SULJETTU 20.12-6.1","menu":[{"name":"Hyvää Joulua! ","price":"Hintaa ei annettu","type":"Lounas"}]},{"name":"Aurum","url":"https://www.karkafeerna.fi/fi/lounas","openHours":"SULJETTU 20.12-6.1","menu":[{"name":"Hyvää Joulua! ","price":"Hintaa ei annettu","type":"Lounas"}]},{"name":"Aurum Bistro","url":"https://www.karkafeerna.fi/fi/lounas","openHours":"SULJETTU 14.12-06.01","menu":[{"name":"Hyvää Joulua! ","price":"Hintaa ei annettu","type":"Lounas"}]},{"name":"Kåren","url":"https://www.karkafeerna.fi/fi/lounas","openHours":"SULJETTU 20.12-6.1","menu":[{"name":"Hyvää Joulua! ","price":"Hintaa ei annettu","type":"Lounas"}]},{"name":"Assarin Ullakko","url":"https://www.unica.fi/ravintolat/Yliopisto/assarin-ullakko/","openHours":"10.30-19.45","menu":[{"name":"Tomaattista tofu-kasviskastiketta (*, A, G, ILM, L, M, Veg, VS)\nTummaa riisiä (*, G, L, M, Veg)","price":"2,95 / 7,70 / 9,20","type":"BRYGGE"},{"name":"Broileria currykastikkeessa (*, A, G, L)","price":"2,95 / 7,70 / 9,20","type":"ASEMA 1-2 10:30-17:45"},{"name":"Jauhelihapyöryköitä pippurikastikkeessa (A,L) ()","price":"2,95 / 7,70 / 9,20","type":"ASEMA 1-2  10:30-16:00"}]},{"name":"Macciavelli","url":"https://www.unica.fi/ravintolat/Yliopisto/Macciavelli/","openHours":"10.30-15.00","menu":[{"name":"Halloumipizzaa, semikuivattua tomaattia ja pikkelöityä punasipulia (A, VS)","price":"2,95 / 6,50 / 7,70 / 9,20","type":"KASVISLOUNAS"},{"name":"Kasviskroketteja \t(*, G, ILM, L, M, Veg, VS) ()\nChili-hummusta (A, G, VEG, VS) ()\nPaahdettua perunaa (*, G, ILM, L, M, Veg)","price":"2,95 / 6,50 / 7,70 / 9,20","type":"KASVISLOUNAS"},{"name":"Rapeita kalapaloja (A, L) ()\nTilli-jogurttikastiketta (A, G, L) ()\nPaahdettua perunaa (A, G, VEG) ()","price":"2,95 / 6,50 / 7,70 / 9,20","type":"LOUNAS"}]},{"name":"Galilei","url":"https://www.unica.fi/ravintolat/Yliopisto/galilei/","openHours":"Ei lounasta tänään","menu":[]},{"name":"Deli Pharma","url":"https://www.unica.fi/ravintolat/Kupittaa/deli-pharma/","openHours":"10:30-14:00","menu":[{"name":"Härkistä teriyaki (*, A, G, ILM, L, M, Veg)\nTummaa riisiä (*, G, L, M, Veg)","price":"2,95 / 9,20","type":"KASVISLOUNAS"},{"name":"Jauhelihapihvejä (*, A, L, M)\nPippurikastiketta (*, A, ILM, L)\nKeitettyjä perunoita (*, A, G, ILM, L, M, Veg)","price":"2,95 / 9,20","type":"LOUNAS"},{"name":"Rapeaa kalaa juustotäytteellä (A, ILM, VL)\nPaahdettua perunaa ja juureksia (*, G, ILM, L, M, Veg)","price":"5,60 / 10,70 / 13,40 (buffet)","type":"BISTRO"},{"name":"Paahdettua kaalia ja porkkanaa (G, L, M, Veg)","price":"Hintaa ei annettu","type":"LÄMMIN KASVISLISUKE"},{"name":"Maisemakahvilan mustikkapiirakka (L) ()","price":"1,80","type":"JÄLKIRUOKA"}]},{"name":"Delica","url":"https://www.unica.fi/ravintolat/Kupittaa/delica/","openHours":"10:30-16:00","menu":[{"name":"Rapeaa kalaa juustotäytteellä (A, ILM, VL)\nPaahdettua perunaa ja juureksia (*, G, ILM, L, M, Veg)","price":"5,60 / 10,70 / 13,40 (buffet)","type":"BISTRO"},{"name":"Härkistä teriyaki (*, A, G, ILM, L, M, Veg)\nTummaa riisiä (*, G, L, M, Veg)","price":"2,95 / 9,20","type":"KASVISLOUNAS"},{"name":"Jauhelihapihvejä (*, A, L, M)\nPippurikastiketta (*, A, ILM, L)\nKeitettyjä perunoita (*, A, G, ILM, L, M, Veg)","price":"2,95 / 9,20","type":"LOUNAS1"},{"name":"Maisemakahvilan mustikkapiirakka (L) ()","price":"1,80","type":"JÄLKIRUOKA"}]},{"name":"Kisälli","url":"https://www.unica.fi/ravintolat/Kupittaa/kisalli/","openHours":"10.30-13.30 (vain asema 1)","menu":[{"name":"Kreikkalaista fetapataa (*, A, ILM, VL)\nLuomutäysjyväpastaa (*, A, ILM, L, M, Veg)","price":"2,95 / 6,50 / 7,70 / 9,20","type":"ASEMA 1 (tarjolla ma-to 10.30-14.30, pe 10.30-14)"},{"name":"Jauhelihapihvejä ja metsäsienikastiketta (*, A, L)\nPaahdettua perunaa (*, G, ILM, L, M, Veg)","price":"2,95 / 6,50 / 7,70 / 9,20","type":"ASEMA 1 (tarjolla ma-to 10.30-14.30, pe 10.30-14)."},{"name":"Vaniljakermavaahtoa (A, G, L)","price":"1,50 / 1,80","type":"JÄLKIRUOKA"},{"name":"Juustopaneroitua broilerinfileetä (*, A, L)\nTzatsiki-jogurttia (*, A, G, L, VS)\nPaahdettua perunaa (*, G, ILM, L, M, Veg)\nSatokauden kasviksia (G, L, M, Veg)","price":"12,20","type":"KAIVOMESTARIN LOUNAS (tarjolla ma-to 11--14, pe 11-13.30)"}]},{"name":"Sigyn","url":"https://www.unica.fi/ravintolat/taidekampus/Sigyn/","openHours":"11.00-14.00","menu":[{"name":"Riisipuuroa (A, G, L)\nMansikkakeittoa (G, L, M, Veg)\nKaneli-sokeria (G, L, M, Veg)","price":"2,95  / 7,70 / 10,10","type":"Lounas"}]},{"name":"Unican Kulma","url":"https://www.unica.fi/ravintolat/Muut/unican-kulma/","openHours":"11:00-18:00","menu":[{"name":"Kasvisbolognesea\n (*, A, G, ILM, L, M, Veg)\nLuomutäysjyväpastaa\n (*, A, ILM, L, M, Veg)","price":"2,95/10,10","type":"LOUNAS"},{"name":"Pyttipannua (G, L, M)","price":"2,95/10,10","type":"LOUNAS"},{"name":"Crispy chicken (G, L, M)\nLohkoperunoita (G, ILM, L, M, Veg)\nAurajuustomajoneesia (A, G, L)\nSatokauden kasviksia\n (G, L, M, Veg)","price":"5,60/13,20","type":"KULMAN  DELI LOUNAS"}]},{"name":"Flavoria","url":"https://www.sodexo.fi/ravintolat/flavoria-medisiina-d","openHours":"Lounas MA-PE 10:30-13:30\nKahvila MA-TO 07:30-15:30\nKahvila PE 07:30-14:30","menu":[{"name":"Linssi-pinaattikormaa ja paahdettua perunaa","price":"2,95 € / 9,35 €","type":"FROM THE FIELD-VEGAN"},{"name":"Lohikeitto","price":"2,95 € / 9,35 €","type":"From our favorites 1"},{"name":"Päivän patonki: Broileri","price":"2,95 € / 7,80 €","type":"FROM OUR BAKERY (kahvilasta)"},{"name":"Pizza Mexicana (pepperoni-ananas-jalapeno)","price":"5,60 € / 10,90 €","type":"FROM THE KITCHEN (grillistä)"},{"name":"Pizza Melanzane (munakoiso-paprika-punasipuli)","price":"5,60 € / 10,90 €","type":"FROM THE KITCHEN VEGAN"}]}]